ryd/__init__.py
ryd/__main__.py
ryd/classes_0_1.py
ryd/loadrst.py
ryd/ryd.py
ryd/sys_stdout.py
ryd/_convertor/__init__.py
ryd/_convertor/_base.py
ryd/_convertor/markdown.py
ryd/_convertor/restructuredtext.py
ryd/_convertor/roundtrip.py
ryd/_convertor/stackoverflow.py
ryd/_tag/__init__.py
ryd/_tag/_handler.py
ryd/_tag/changelog.py
ryd/_tag/code.py
ryd/_tag/comment.py
ryd/_tag/inc.py
ryd/_tag/lastcompile.py
ryd/_tag/nim.py
ryd/_tag/python.py
ryd/_tag/stdout.py
ryd/_tag/table.py
ryd/_tag/toc.py
ryd/_tag/yamlout.py
ryd/_tag/zig.py
ryd/_tag/zsh.py
ryd-0.9.2.dist-info/LICENSE
ryd-0.9.2.dist-info/METADATA
ryd-0.9.2.dist-info/WHEEL
ryd-0.9.2.dist-info/entry_points.txt
ryd-0.9.2.dist-info/top_level.txt
ryd-0.9.2.dist-info/RECORD
