Metadata-Version: 2.1
Name: ryd
Version: 0.9.2
Summary: Ruamel Yaml Doc preprocessor (pronounced: /rɑɪt/, like the verb "write")
Author: Anthon van der Neut
Author-email: a.van.der.neut@ruamel.eu
License: MIT
Project-URL: Home, https://sourceforge.net/p/ryd/
Project-URL: Source, https://sourceforge.net/p/ryd/code/ci/default/tree/
Project-URL: Tracker, https://sourceforge.net/p/ryd/tickets/
Keywords: restructuredtext markdown markup preprocessing
Classifier: Development Status :: 4 - Beta
Classifier: Intended Audience :: Developers
Classifier: License :: OSI Approved :: MIT License
Classifier: Operating System :: OS Independent
Classifier: Programming Language :: Python
Requires-Python: >=3
License-File: LICENSE
Requires-Dist: ruamel.std.pathlib
Requires-Dist: ruamel.yaml
Requires-Dist: ruamel.yaml.split
